videoToFrames/__init__.py
videoToFrames/__main__.py
videoToFrames/breaker.py
videoToFrames/config.toml
break_video_to_frames-1.0.0.dist-info/LICENSE
break_video_to_frames-1.0.0.dist-info/METADATA
break_video_to_frames-1.0.0.dist-info/WHEEL
break_video_to_frames-1.0.0.dist-info/entry_points.txt
break_video_to_frames-1.0.0.dist-info/top_level.txt
break_video_to_frames-1.0.0.dist-info/RECORD
