Metadata-Version: 2.1
Name: break-video-to-frames
Version: 1.0.0
Summary: Break a video to it's frames.
Author-email: Alireza Nematollahi <alireza.tehran2020@gmail.com>
License: MIT License
Project-URL: Homepage, https://github.com/alirezanmt/video_to_frames
Keywords: breaker,videoToFrames,videoBreaker
Classifier: License :: OSI Approved :: MIT License
Classifier: Programming Language :: Python
Classifier: Programming Language :: Python :: 3
Requires-Python: >=3.9
License-File: LICENSE
Requires-Dist: opencv-python
Requires-Dist: tomli ; python_version < "3.11"
Provides-Extra: dev
Requires-Dist: pip-tools ; extra == 'dev'
Requires-Dist: pytest ; extra == 'dev'
